nhdpy/__init__.py
nhdpy/nhdpy.py
nhdpy-0.1.1.dist-info/LICENSE
nhdpy-0.1.1.dist-info/METADATA
nhdpy-0.1.1.dist-info/WHEEL
nhdpy-0.1.1.dist-info/top_level.txt
nhdpy-0.1.1.dist-info/RECORD
