Metadata-Version: 2.1
Name: nhdpy
Version: 0.1.1
Summary: A python port of the nhdR package for querying, downloading, and networking the National Hydrography Dataset (NHD) dataset
Home-page: https://github.com/jsta/nhdpy
Author: Jemma Stachelek
Author-email: stachel2@msu.edu
License: MIT license
Keywords: nhdpy
Platform: UNKNOWN
Classifier: Development Status :: 2 - Pre-Alpha
Classifier: Intended Audience :: Developers
Classifier: License :: OSI Approved :: MIT License
Classifier: Natural Language :: English
Classifier: Programming Language :: Python :: 3
Classifier: Programming Language :: Python :: 3.5
Classifier: Programming Language :: Python :: 3.6
Classifier: Programming Language :: Python :: 3.7
Classifier: Programming Language :: Python :: 3.8
Requires-Python: >=3.5
